setup.py
cratis_cms/__init__.py
cratis_cms/features.py
django_cratis_cms.egg-info/PKG-INFO
django_cratis_cms.egg-info/SOURCES.txt
django_cratis_cms.egg-info/dependency_links.txt
django_cratis_cms.egg-info/requires.txt
django_cratis_cms.egg-info/top_level.txt