Metadata-Version: 1.0
Name: django-cratis-cms
Version: 0.1.1
Summary: Integrates django-cms into cratis application
Home-page: UNKNOWN
Author: Alex Rudakov
Author-email: ribozz@gmail.com
License: MIT
Platform: UNKNOWN
